__init__.py
main.py
ui_main.py
core/app_globals.py
core/app_signals.py
core/bk_ut.py
core/check_update.py
core/compact_list.py
core/create_db.py
core/db_ut.py
core/dir_model.py
core/drag_drop.py
core/edit_delegates.py
core/file_model.py
core/history.py
core/linux_menu.py
core/load_files.py
core/low_bk.py
core/reports.py
core/sho.py
core/win_menu.py
core/win_win.py
md2fileo-1.4.1.dist-info/licenses/LICENSE.txt
qss/__init__.py
tug/__init__.py
widgets/about.py
widgets/cust_msgbox.py
widgets/custom_grips.py
widgets/dir_tree_cycle.py
widgets/dup.py
widgets/file_authors.py
widgets/file_data.py
widgets/file_info.py
widgets/file_note.py
widgets/file_notes.py
widgets/file_tags.py
widgets/filter_setup.py
widgets/fold_container.py
widgets/foldable.py
widgets/locations.py
widgets/note_editor.py
widgets/open_db.py
widgets/preferences.py
widgets/scan_disk_for_files.py
widgets/search_files.py
widgets/srch_in_notes.py
widgets/ui_about.py
widgets/ui_cust_msgbox.py
widgets/ui_dup.py
widgets/ui_file_note.py
widgets/ui_fold_container.py
widgets/ui_foldable.py
widgets/ui_notes.py
widgets/ui_open_db.py
widgets/ui_pref.py
widgets/ui_scan_disk.py
widgets/ui_set_filter.py
widgets/workers.py
md2fileo-1.4.1.dist-info/METADATA
md2fileo-1.4.1.dist-info/WHEEL
md2fileo-1.4.1.dist-info/top_level.txt
md2fileo-1.4.1.dist-info/RECORD
