Metadata-Version: 2.4
Name: md2fileo
Version: 1.4.1
Summary: Yet another file organizer
Requires-Python: >=3.13
License-File: LICENSE.txt
Requires-Dist: loguru>=0.7.3
Requires-Dist: pyqt6<6.8.0
Requires-Dist: apsw>=3.47.1.0
Requires-Dist: markdown>=3.7
Dynamic: license-file
